pythonping/__init__.py
pythonping/executor.py
pythonping/icmp.py
pythonping/network.py
pythonping/payload_provider.py
pythonping/utils.py
pythonping-1.1.3.dist-info/LICENSE
pythonping-1.1.3.dist-info/METADATA
pythonping-1.1.3.dist-info/WHEEL
pythonping-1.1.3.dist-info/top_level.txt
pythonping-1.1.3.dist-info/RECORD
