Metadata-Version: 2.1
Name: pythonping
Version: 1.1.3
Summary: A simple way to ping in Python
Home-page: https://github.com/alessandromaggio/pythonping
Author: Alessandro Maggio
Author-email: me@alessandromaggio.com
License: MIT
Keywords: ping,icmp,network
Classifier: Development Status :: 5 - Production/Stable
Classifier: Intended Audience :: System Administrators
Classifier: Natural Language :: English
License-File: LICENSE
